pyemv/__init__.py
pyemv/ac.py
pyemv/cvn.py
pyemv/cvv.py
pyemv/kd.py
pyemv/mac.py
pyemv/py.typed
pyemv/sm.py
pyemv/tlv.py
pyemv/tools.py
pyemv-1.5.0.dist-info/LICENSE.md
pyemv-1.5.0.dist-info/METADATA
pyemv-1.5.0.dist-info/WHEEL
pyemv-1.5.0.dist-info/top_level.txt
pyemv-1.5.0.dist-info/RECORD
